smithsonian_queri/.DS_Store
smithsonian_queri/__init__.py
smithsonian_queri/smithsonian_queri.py
smithsonian_queri-0.1.0.dist-info/LICENSE
smithsonian_queri-0.1.0.dist-info/WHEEL
smithsonian_queri-0.1.0.dist-info/METADATA
smithsonian_queri-0.1.0.dist-info/RECORD
